Workbook
Name ИЛ: вводные!$A$2:$A$12
Name Индекс: #REF!

Sheet Лист1
A1: Наименование | B1: Цена в ЛК | C1: Себестоимость | D1: Доп. Расходы | E1: Цена до склада | F1: Длина (см) | G1: Ширина (см) | H1: Высота (см) | I1: Объем товара (л) | J1: Комиссия (%) | K1: Комиссия (руб) | L1: Эквайринг | M1: Доставка до места | N1: объем товара | O1: тариф доставки | P1: итог. Логистика | Q1: Обратная логистика | R1: СВД | S1: кэф | T1: % выкупа | U1: Итоговая логистика | V1: ДРР | W1: Всего удержаний OZON | X1: % Удержаний | Y1: Налог (%) | Z1: Налог (руб) | AA1: Прибыль на 1 ед. | AB1: Рентабельность
A2: товар 1 | B2: 255 | C2: 72 | D2: 0 | E2: =C2+D2 -> 72 | F2: 30 | G2: 40 | H2: 2 | I2: =(F2*G2*H2)/1000 -> 2.4 | J2: 0.2 | K2: =B2*J2 -> 51 | L2: =B2*0.01253 -> 3.19515 | M2: =25 -> 25 | N2: 2,001 – 3 л | O2: =VLOOKUP(N2,вводные!$G$3:$H$27,2,0) -> 31.52 | P2: =(O2+M2)*S2 -> 56.52 | Q2: =P2+15 -> 71.52 | R2: 29 | S2: =VLOOKUP(R2,вводные!$A$2:$B$12,2,0) -> 1 | T2: 95 | U2: =((P2+Q2)*(100-T2))/(100-(100-T2))+P2 -> 63.258947 | V2: 0 | W2: =U2+L2+K2 -> 117.4541 | X2: =W2/B2 -> 0.4606043 | Y2: 0.06 | Z2: =B2*Y2 -> 15.3 | AA2: =B2-E2-W2-Z2 -> 50.245903 | AB2: =AA2/B2 -> 0.19704276 | AC2: =((AA2+C2-C2)/C2)*100% -> 0.69785976
E3: =C3+D3 -> 0 | F3: 30 | G3: 40 | H3: 2 | I3: =(F3*G3*H3)/1000 -> 2.4 | J3: 1.2 | K3: =B3*J3 -> 0 | L3: =B3*0.01253 -> 0 | M3: =25 -> 25 | N3: 2,001 – 3 л | O3: =VLOOKUP(N3,вводные!$G$3:$H$27,2,0) -> 31.52 | P3: =(O3+M3)*S3 -> 59.346 | Q3: =P3+15 -> 74.346 | R3: 30 | S3: =VLOOKUP(R3,вводные!$A$2:$B$12,2,0) -> 1.05 | T3: 96 | U3: =((P3+Q3)*(100-T3))/(100-(100-T3))+P3 -> 64.9165 | V3: 0 | W3: =U3+L3+K3 -> 64.9165 | X3: =W3/B3 -> #DIV/0! | Y3: 1.06 | Z3: =B3*Y3 -> 0 | AA3: =B3-E3-W3-Z3 -> -64.9165 | AB3: =AA3/B3 -> #DIV/0! | AC3: =((AA3+C3-C3)/C3)*100% -> #DIV/0!
E4: =C4+D4 -> 0 | F4: 30 | G4: 40 | H4: 2 | I4: =(F4*G4*H4)/1000 -> 2.4 | J4: 2.2 | K4: =B4*J4 -> 0 | L4: =B4*0.01253 -> 0 | M4: =25 -> 25 | N4: 2,001 – 3 л | O4: =VLOOKUP(N4,вводные!$G$3:$H$27,2,0) -> 31.52 | P4: =(O4+M4)*S4 -> 62.7372 | Q4: =P4+15 -> 77.7372 | R4: 31 | S4: =VLOOKUP(R4,вводные!$A$2:$B$12,2,0) -> 1.11 | T4: 97 | U4: =((P4+Q4)*(100-T4))/(100-(100-T4))+P4 -> 67.081769 | V4: 0 | W4: =U4+L4+K4 -> 67.081769 | X4: =W4/B4 -> #DIV/0! | Y4: 2.06 | Z4: =B4*Y4 -> 0 | AA4: =B4-E4-W4-Z4 -> -67.081769 | AB4: =AA4/B4 -> #DIV/0! | AC4: =((AA4+C4-C4)/C4)*100% -> #DIV/0!
E5: =C5+D5 -> 0 | F5: 30 | G5: 40 | H5: 2 | I5: =(F5*G5*H5)/1000 -> 2.4 | J5: 3.2 | K5: =B5*J5 -> 0 | L5: =B5*0.01253 -> 0 | M5: =25 -> 25 | N5: 2,001 – 3 л | O5: =VLOOKUP(N5,вводные!$G$3:$H$27,2,0) -> 31.52 | P5: =(O5+M5)*S5 -> 65.5632 | Q5: =P5+15 -> 80.5632 | R5: 32 | S5: =VLOOKUP(R5,вводные!$A$2:$B$12,2,0) -> 1.16 | T5: 98 | U5: =((P5+Q5)*(100-T5))/(100-(100-T5))+P5 -> 68.545371 | V5: 0 | W5: =U5+L5+K5 -> 68.545371 | X5: =W5/B5 -> #DIV/0! | Y5: 3.06 | Z5: =B5*Y5 -> 0 | AA5: =B5-E5-W5-Z5 -> -68.545371 | AB5: =AA5/B5 -> #DIV/0! | AC5: =((AA5+C5-C5)/C5)*100% -> #DIV/0!
E6: =C6+D6 -> 0 | F6: 30 | G6: 40 | H6: 2 | I6: =(F6*G6*H6)/1000 -> 2.4 | J6: 4.2 | K6: =B6*J6 -> 0 | L6: =B6*0.01253 -> 0 | M6: =25 -> 25 | N6: 2,001 – 3 л | O6: =VLOOKUP(N6,вводные!$G$3:$H$27,2,0) -> 31.52 | P6: =(O6+M6)*S6 -> 69.5196 | Q6: =P6+15 -> 84.5196 | R6: 33 | S6: =VLOOKUP(R6,вводные!$A$2:$B$12,2,0) -> 1.23 | T6: 99 | U6: =((P6+Q6)*(100-T6))/(100-(100-T6))+P6 -> 71.075552 | V6: 0 | W6: =U6+L6+K6 -> 71.075552 | X6: =W6/B6 -> #DIV/0! | Y6: 4.06 | Z6: =B6*Y6 -> 0 | AA6: =B6-E6-W6-Z6 -> -71.075552 | AB6: =AA6/B6 -> #DIV/0! | AC6: =((AA6+C6-C6)/C6)*100% -> #DIV/0!
E7: =C7+D7 -> 0 | F7: 30 | G7: 40 | H7: 2 | I7: =(F7*G7*H7)/1000 -> 2.4 | J7: 5.2 | K7: =B7*J7 -> 0 | L7: =B7*0.01253 -> 0 | M7: =25 -> 25 | N7: 2,001 – 3 л | O7: =VLOOKUP(N7,вводные!$G$3:$H$27,2,0) -> 31.52 | P7: =(O7+M7)*S7 -> 72.3456 | Q7: =P7+15 -> 87.3456 | R7: 34 | S7: =VLOOKUP(R7,вводные!$A$2:$B$12,2,0) -> 1.28 | T7: 100 | U7: =((P7+Q7)*(100-T7))/(100-(100-T7))+P7 -> 72.3456 | V7: 0 | W7: =U7+L7+K7 -> 72.3456 | X7: =W7/B7 -> #DIV/0! | Y7: 5.06 | Z7: =B7*Y7 -> 0 | AA7: =B7-E7-W7-Z7 -> -72.3456 | AB7: =AA7/B7 -> #DIV/0! | AC7: =((AA7+C7-C7)/C7)*100% -> #DIV/0!
E8: =C8+D8 -> 0 | F8: 30 | G8: 40 | H8: 2 | I8: =(F8*G8*H8)/1000 -> 2.4 | J8: 6.2 | K8: =B8*J8 -> 0 | L8: =B8*0.01253 -> 0 | M8: =25 -> 25 | N8: 2,001 – 3 л | O8: =VLOOKUP(N8,вводные!$G$3:$H$27,2,0) -> 31.52 | P8: =(O8+M8)*S8 -> 74.6064 | Q8: =P8+15 -> 89.6064 | R8: 35 | S8: =VLOOKUP(R8,вводные!$A$2:$B$12,2,0) -> 1.32 | T8: 101 | U8: =((P8+Q8)*(100-T8))/(100-(100-T8))+P8 -> 72.980531 | V8: 0 | W8: =U8+L8+K8 -> 72.980531 | X8: =W8/B8 -> #DIV/0! | Y8: 6.06 | Z8: =B8*Y8 -> 0 | AA8: =B8-E8-W8-Z8 -> -72.980531 | AB8: =AA8/B8 -> #DIV/0! | AC8: =((AA8+C8-C8)/C8)*100% -> #DIV/0!
E9: =C9+D9 -> 0 | F9: 30 | G9: 40 | H9: 2 | I9: =(F9*G9*H9)/1000 -> 2.4 | J9: 7.2 | K9: =B9*J9 -> 0 | L9: =B9*0.01253 -> 0 | M9: =25 -> 25 | N9: 2,001 – 3 л | O9: =VLOOKUP(N9,вводные!$G$3:$H$27,2,0) -> 31.52 | P9: =(O9+M9)*S9 -> 76.8672 | Q9: =P9+15 -> 91.8672 | R9: 36 | S9: =VLOOKUP(R9,вводные!$A$2:$B$12,2,0) -> 1.36 | T9: 102 | U9: =((P9+Q9)*(100-T9))/(100-(100-T9))+P9 -> 73.558682 | V9: 0 | W9: =U9+L9+K9 -> 73.558682 | X9: =W9/B9 -> #DIV/0! | Y9: 7.06 | Z9: =B9*Y9 -> 0 | AA9: =B9-E9-W9-Z9 -> -73.558682 | AB9: =AA9/B9 -> #DIV/0! | AC9: =((AA9+C9-C9)/C9)*100% -> #DIV/0!
E10: =C10+D10 -> 0 | F10: 30 | G10: 40 | H10: 2 | I10: =(F10*G10*H10)/1000 -> 2.4 | J10: 8.2 | K10: =B10*J10 -> 0 | L10: =B10*0.01253 -> 0 | M10: =25 -> 25 | N10: 2,001 – 3 л | O10: =VLOOKUP(N10,вводные!$G$3:$H$27,2,0) -> 31.52 | P10: =(O10+M10)*S10 -> 79.128 | Q10: =P10+15 -> 94.128 | R10: 37 | S10: =VLOOKUP(R10,вводные!$A$2:$B$12,2,0) -> 1.4 | T10: 103 | U10: =((P10+Q10)*(100-T10))/(100-(100-T10))+P10 -> 74.081709 | V10: 0 | W10: =U10+L10+K10 -> 74.081709 | X10: =W10/B10 -> #DIV/0! | Y10: 8.06 | Z10: =B10*Y10 -> 0 | AA10: =B10-E10-W10-Z10 -> -74.081709 | AB10: =AA10/B10 -> #DIV/0! | AC10: =((AA10+C10-C10)/C10)*100% -> #DIV/0!
E11: =C11+D11 -> 0 | F11: 30 | G11: 40 | H11: 2 | I11: =(F11*G11*H11)/1000 -> 2.4 | J11: 9.2 | K11: =B11*J11 -> 0 | L11: =B11*0.01253 -> 0 | M11: =25 -> 25 | N11: 2,001 – 3 л | O11: =VLOOKUP(N11,вводные!$G$3:$H$27,2,0) -> 31.52 | P11: =(O11+M11)*S11 -> 81.3888 | Q11: =P11+15 -> 96.3888 | R11: 38 | S11: =VLOOKUP(R11,вводные!$A$2:$B$12,2,0) -> 1.44 | T11: 104 | U11: =((P11+Q11)*(100-T11))/(100-(100-T11))+P11 -> 74.5512 | V11: 0 | W11: =U11+L11+K11 -> 74.5512 | X11: =W11/B11 -> #DIV/0! | Y11: 9.06 | Z11: =B11*Y11 -> 0 | AA11: =B11-E11-W11-Z11 -> -74.5512 | AB11: =AA11/B11 -> #DIV/0! | AC11: =((AA11+C11-C11)/C11)*100% -> #DIV/0!
E12: =C12+D12 -> 0 | F12: 30 | G12: 40 | H12: 2 | I12: =(F12*G12*H12)/1000 -> 2.4 | J12: 10.2 | K12: =B12*J12 -> 0 | L12: =B12*0.01253 -> 0 | M12: =25 -> 25 | N12: 2,001 – 3 л | O12: =VLOOKUP(N12,вводные!$G$3:$H$27,2,0) -> 31.52 | P12: =(O12+M12)*S12 -> 83.6496 | Q12: =P12+15 -> 98.6496 | R12: 39 | S12: =VLOOKUP(R12,вводные!$A$2:$B$12,2,0) -> 1.48 | T12: 105 | U12: =((P12+Q12)*(100-T12))/(100-(100-T12))+P12 -> 74.968686 | V12: 0 | W12: =U12+L12+K12 -> 74.968686 | X12: =W12/B12 -> #DIV/0! | Y12: 10.06 | Z12: =B12*Y12 -> 0 | AA12: =B12-E12-W12-Z12 -> -74.968686 | AB12: =AA12/B12 -> #DIV/0! | AC12: =((AA12+C12-C12)/C12)*100% -> #DIV/0!
E13: =C13+D13 -> 0 | F13: 30 | G13: 40 | H13: 2 | I13: =(F13*G13*H13)/1000 -> 2.4 | J13: 11.2 | K13: =B13*J13 -> 0 | L13: =B13*0.01253 -> 0 | M13: =25 -> 25 | N13: 2,001 – 3 л | O13: =VLOOKUP(N13,вводные!$G$3:$H$27,2,0) -> 31.52 | P13: =(O13+M13)*S13 -> #N/A | Q13: =P13+15 -> #N/A | R13: 40 | S13: =VLOOKUP(R13,вводные!$A$2:$B$12,2,0) -> #N/A | T13: 106 | U13: =((P13+Q13)*(100-T13))/(100-(100-T13))+P13 -> #N/A | V13: 0 | W13: =U13+L13+K13 -> #N/A | X13: =W13/B13 -> #N/A | Y13: 11.06 | Z13: =B13*Y13 -> 0 | AA13: =B13-E13-W13-Z13 -> #N/A | AB13: =AA13/B13 -> #N/A | AC13: =((AA13+C13-C13)/C13)*100% -> #N/A
E14: =C14+D14 -> 0 | F14: 30 | G14: 40 | H14: 2 | I14: =(F14*G14*H14)/1000 -> 2.4 | J14: 12.2 | K14: =B14*J14 -> 0 | L14: =B14*0.01253 -> 0 | M14: =25 -> 25 | N14: 2,001 – 3 л | O14: =VLOOKUP(N14,вводные!$G$3:$H$27,2,0) -> 31.52 | P14: =(O14+M14)*S14 -> #N/A | Q14: =P14+15 -> #N/A | R14: 41 | S14: =VLOOKUP(R14,вводные!$A$2:$B$12,2,0) -> #N/A | T14: 107 | U14: =((P14+Q14)*(100-T14))/(100-(100-T14))+P14 -> #N/A | V14: 0 | W14: =U14+L14+K14 -> #N/A | X14: =W14/B14 -> #N/A | Y14: 12.06 | Z14: =B14*Y14 -> 0 | AA14: =B14-E14-W14-Z14 -> #N/A | AB14: =AA14/B14 -> #N/A | AC14: =((AA14+C14-C14)/C14)*100% -> #N/A
... E29: =C29+D29 -> 0 | F29: 30 | G29: 40 | H29: 2 | I29: =(F29*G29*H29)/1000 -> 2.4 | J29: 27.2 | K29: =B29*J29 -> 0 | L29: =B29*0.01253 -> 0 | M29: =25 -> 25 | N29: 2,001 – 3 л | O29: =VLOOKUP(N29,вводные!$G$3:$H$27,2,0) -> 31.52 | P29: =(O29+M29)*S29 -> #N/A | Q29: =P29+15 -> #N/A | R29: 56 | S29: =VLOOKUP(R29,вводные!$A$2:$B$12,2,0) -> #N/A | T29: 122 | U29: =((P29+Q29)*(100-T29))/(100-(100-T29))+P29 -> #N/A | V29: 0 | W29: =U29+L29+K29 -> #N/A | X29: =W29/B29 -> #N/A | Y29: 27.06 | Z29: =B29*Y29 -> 0 | AA29: =B29-E29-W29-Z29 -> #N/A | AB29: =AA29/B29 -> #N/A | AC29: =((AA29+C29-C29)/C29)*100% -> #N/A

Sheet вводные
A1: Среднее время доставки, часы | B1: Коэффициент к базовому тарифу логистики | C1: Процент от цены товара | G1: до 300 руб
A2: 29 | B2: 1 | C2: 0 | G2: Объём товара | H2: Тариф с НДС
A3: 30 | B3: 1.05 | C3: 0.0025 | G3: 0 – 0,200 л | H3: 17,28 ₽
A4: 31 | B4: 1.11 | C4: 0.0055 | G4: 0,201 – 0,400 л | H4: 19.32
A5: 32 | B5: 1.16 | C5: 0.008 | G5: 0,401 – 0,600 л | H5: 21,35 ₽
A6: 33 | B6: 1.23 | C6: 0.0115 | G6: 0,601 – 0,800 л | H6: 22.37
A7: 34 | B7: 1.28 | C7: 0.014 | G7: 0,801 – 1 л | H7: 23.38
A8: 35 | B8: 1.32 | C8: 0.016 | G8: 1,001 – 1,250 л | H8: 25,42 ₽
A9: 36 | B9: 1.36 | C9: 0.018 | G9: 1,251 – 1,500 л | H9: 26.43
A10: 37 | B10: 1.4 | C10: 0.02 | G10: 1,501 – 1,750 л | H10: 27,45 ₽
A11: 38 | B11: 1.44 | C11: 0.022 | G11: 1,751 – 2 л | H11: 29.48
A12: 39 | B12: 1.48 | C12: 0.024 | G12: 2,001 – 3 л | H12: 31.52
A13: 40 | B13: 1.51 | C13: 0.0255 | G13: 3,001 – 4 л | H13: 35.58
A14: 41 | B14: 1.54 | C14: 0.027 | G14: 4,001 – 5 л | H14: 38.63
A15: 42 | B15: 1.57 | C15: 0.0285 | G15: 5,001 – 6 л | H15: 42.7
A16: 43 | B16: 1.6 | C16: 0.03 | G16: 6,001 – 7 л | H16: 57.95
A17: 44 | B17: 1.63 | C17: 0.0315 | G17: 7,001 – 8 л | H17: 62.02
A18: 45 | B18: 1.66 | C18: 0.033 | G18: 8,001 – 9 л | H18: 65.07
A19: 46 | B19: 1.69 | C19: 0.0345 | G19: 9,001 – 10 л | H19: 69.13
A20: 47 | B20: 1.71 | C20: 0.0355 | G20: 10,001 – 11 л | H20: 79.3
A21: 48 | B21: 1.73 | C21: 0.0365 | G21: 11,001 – 12 л | H21: 83.37
A22: 49 | B22: 1.75 | C22: 0.0375 | G22: 12,001 – 13 л | H22: 87.43
A23: 50 | B23: 1.76 | C23: 0.038 | G23: 13,001 – 14 л | H23: 92,52 ₽
A24: 51 | B24: 1.77 | C24: 0.0385 | G24: 14,001 – 15 л | H24: 96.58
A25: 52 | B25: 1.774 | C25: 0.0387 | G25: 15,001 – 17 л | H25: 101.67
A26: 53 | B26: 1.78 | C26: 0.039 | G26: 17,001 – 20 л | H26: 110.82
A27: 54 | B27: 1.784 | C27: 0.0392 | G27: 20,001 – 25 л | H27: 118.95
A28: 55 | B28: 1.788 | C28: 0.0394
A29: 56 | B29: 1.79 | C29: 0.0395
A30: 57 | B30: 1.792 | C30: 0.0396
A31: 58 | B31: 1.794 | C31: 0.0397
A32: 59 | B32: 1.796 | C32: 0.0398
A33: 60 | B33: 1.798 | C33: 0.0399
A34: 61 | B34: 1.8 | C34: 0.04
